erb/__init__.py
erb/_parse.py
erb/yml.py
pyyaml_erb-1.0.6.dist-info/LICENSE.txt
pyyaml_erb-1.0.6.dist-info/METADATA
pyyaml_erb-1.0.6.dist-info/WHEEL
pyyaml_erb-1.0.6.dist-info/entry_points.txt
pyyaml_erb-1.0.6.dist-info/top_level.txt
pyyaml_erb-1.0.6.dist-info/RECORD
